fuck_python_str-0.1.1.dist-info/METADATA
fuck_python_str-0.1.1.dist-info/RECORD
fuck_python_str-0.1.1.dist-info/WHEEL
fuck_python_str-0.1.1.dist-info/top_level.txt
fuck_str/__init__.py
