Metadata-Version: 2.1
Name: fuck-python-str
Version: 0.1.1
Summary: helper to make compatible string in python2 and python3
Home-page: https://github.com/weaming/fuck-python-str
Author: weaming
Author-email: garden.yuen@gmail.com
License: UNKNOWN
Project-URL: Source, https://github.com/weaming/fuck-python-str
Project-URL: Bug Reports, https://github.com/weaming/fuck-python-str
Platform: UNKNOWN
